{
  "main": {
    "id": "54971fa9b3654cf5",
    "type": "split",
    "children": [
      {
        "id": "f021bd8d7e327b35",
        "type": "tabs",
        "children": [
          {
            "id": "ec972c18dd72d892",
            "type": "leaf",
            "state": {
              "type": "markdown",
              "state": {
                "file": "Notes/006-ai/环镜搭建.md",
                "mode": "source",
                "source": true
              }
            }
          },
          {
            "id": "0c0d25faeebc32e8",
            "type": "leaf",
            "state": {
              "type": "markdown",
              "state": {
                "file": "Notes/006-ai/环镜搭建.md",
                "mode": "source",
                "source": false
              }
            }
          }
        ],
        "currentTab": 1
      }
    ],
    "direction": "vertical"
  },
  "left": {
    "id": "0df883ba4d35bb82",
    "type": "split",
    "children": [
      {
        "id": "dc544b5d514d5f86",
        "type": "tabs",
        "children": [
          {
            "id": "1811bdc6bf476244",
            "type": "leaf",
            "state": {
              "type": "file-explorer",
              "state": {
                "sortOrder": "alphabetical"
              }
            }
          },
          {
            "id": "773701a6d5c83f5a",
            "type": "leaf",
            "state": {
              "type": "search",
              "state": {
                "query": "",
                "matchingCase": false,
                "explainSearch": false,
                "collapseAll": false,
                "extraContext": false,
                "sortOrder": "alphabetical"
              }
            }
          },
          {
            "id": "f7749baa03cafba7",
            "type": "leaf",
            "state": {
              "type": "bookmarks",
              "state": {}
            }
          }
        ]
      }
    ],
    "direction": "horizontal",
    "width": 320.5
  },
  "right": {
    "id": "33e6a9ce37303beb",
    "type": "split",
    "children": [
      {
        "id": "9d46db5a4b6f0943",
        "type": "tabs",
        "children": [
          {
            "id": "6fab8ff3f77d62cc",
            "type": "leaf",
            "state": {
              "type": "backlink",
              "state": {
                "file": "Notes/006-ai/环镜搭建.md",
                "collapseAll": false,
                "extraContext": false,
                "sortOrder": "alphabetical",
                "showSearch": false,
                "searchQuery": "",
                "backlinkCollapsed": false,
                "unlinkedCollapsed": true
              }
            }
          },
          {
            "id": "ba28b7efcd822576",
            "type": "leaf",
            "state": {
              "type": "outgoing-link",
              "state": {
                "file": "Notes/006-ai/环镜搭建.md",
                "linksCollapsed": false,
                "unlinkedCollapsed": true
              }
            }
          },
          {
            "id": "5711c485da272151",
            "type": "leaf",
            "state": {
              "type": "tag",
              "state": {
                "sortOrder": "alphabetical",
                "useHierarchy": true
              }
            }
          },
          {
            "id": "c5e653a369892aee",
            "type": "leaf",
            "state": {
              "type": "outline",
              "state": {
                "file": "Notes/006-ai/环镜搭建.md"
              }
            }
          },
          {
            "id": "6bb194fee9ede672",
            "type": "leaf",
            "state": {
              "type": "git-view",
              "state": {}
            }
          }
        ],
        "currentTab": 4
      }
    ],
    "direction": "horizontal",
    "width": 262.5
  },
  "left-ribbon": {
    "hiddenItems": {
      "switcher:打开快速切换": false,
      "graph:查看关系图谱": false,
      "canvas:新建白板": false,
      "daily-notes:打开/创建今天的日记": false,
      "templates:插入模板": false,
      "command-palette:打开命令面板": false
    }
  },
  "active": "0c0d25faeebc32e8",
  "lastOpenFiles": [
    "Notes/006-ai/未命名.md",
    "Notes/006-ai/环镜搭建.md",
    "Notes/003-linux/bash/install brew on linux.md",
    "Notes/003-linux/bash/index.md",
    "Notes/006-ai/模型学习技巧.md",
    "Notes/006-ai/无Pytorch情况下只使用tokenizer.md",
    "Notes/006-ai/Apple调用路径猜测.md",
    "Notes/006-ai/AI相关各类内存接口速率.md",
    "Notes/006-ai/qualcomm.md",
    "Notes/006-ai/llama.md",
    "Notes/006-ai/index.md",
    "Notes/006-ai/cnn-yolo-tensor.md",
    "Notes/006-ai/CLIP模型学习.md",
    "Notes/006-ai/a.puml.md",
    "未命名.canvas",
    "Notes/001-modern-computing/022-modern-gpu-3.md",
    "Notes/001-modern-computing/023-memory.md",
    "Notes/005-algorithm/quick_sort.md",
    "Notes/005-algorithm/index.md",
    "Notes/005-algorithm/fuzzy_search.md",
    "Notes/006-ai/img.png",
    "Notes/006-ai/assets/Pasted image 20240613191023.png",
    "Notes/006-ai/assets/JESD250D.pdf",
    "howto.md",
    "Notes/006-ai/assets/Pasted image 20240613174348.png",
    "Notes/006-ai/assets/Pasted image 20240613173926.png",
    "Notes/006-ai/assets/Pasted image 20240613173706.png",
    "Notes/006-ai/assets/Pasted image 20240613172130.png",
    "Notes/006-ai/assets/Pasted image 20240613172020.png",
    "Notes/006-ai/assets/Pasted image 20240613162001.png",
    "Notes/006-ai/assets/Pasted image 20240613160621.png",
    "Notes/006-ai/assets/Pasted image 20240613160328.png",
    "assets/Pasted.md",
    "Notes/006-ai/assets/JESD79-3E.pdf",
    "Notes/006-ai/assets/JESD79-4.pdf",
    "Notes/006-ai/assets/JESD239.01.pdf",
    "Notes/cheatsheets.md",
    "Notes/assets",
    "Notes/006-ai/assets",
    "Notes/002-android/kotlin.md",
    "Notes/998-zhihu/有益却无法去做.md",
    "Notes/998-zhihu/稀缺资源的配置能力.md",
    "Notes/998-zhihu/强大的自我.md"
  ]
}